LICENSE
MANIFEST.in
README
README.md
setup.py
bin/qr-claquet
signalsync/__init__.py
signalsync/__main__.py
signalsync/dtmf.py
signalsync/mobile.py
signalsync/qr.py
signalsync/ts.py
signalsync.egg-info/PKG-INFO
signalsync.egg-info/SOURCES.txt
signalsync.egg-info/dependency_links.txt
signalsync.egg-info/requires.txt
signalsync.egg-info/top_level.txt
signalsync/mobile/cache.appcache
signalsync/mobile/discordtest.html
signalsync/mobile/favicon.ico
signalsync/mobile/icon.svg